pytest_htr/__init__.py
pytest_htr/plugin.py
pytest_htr/serialize.py
pytest_hardware_test_report-0.2.1.dist-info/LICENSE
pytest_hardware_test_report-0.2.1.dist-info/METADATA
pytest_hardware_test_report-0.2.1.dist-info/WHEEL
pytest_hardware_test_report-0.2.1.dist-info/entry_points.txt
pytest_hardware_test_report-0.2.1.dist-info/RECORD
