Metadata-Version: 2.1
Name: pytest-hardware-test-report
Version: 0.2.1
Summary: A simple plugin to use with pytest
License: LICENSE
Author: Matthew Trott
Author-email: trottmpq@gmail.com
Maintainer: Matthew Trott
Maintainer-email: trottmpq@gmail.com
Requires-Python: >=3.8.1,<4.0.0
Classifier: Development Status :: 4 - Beta
Classifier: Framework :: Pytest
Classifier: Intended Audience :: Developers
Classifier: License :: OSI Approved :: MIT License
Classifier: License :: Other/Proprietary License
Classifier: Operating System :: OS Independent
Classifier: Programming Language :: Python
Classifier: Programming Language :: Python :: 3
Classifier: Programming Language :: Python :: 3.9
Classifier: Programming Language :: Python :: 3.10
Classifier: Programming Language :: Python :: 3.11
Classifier: Programming Language :: Python :: 3.12
Classifier: Programming Language :: Python :: 3 :: Only
Classifier: Programming Language :: Python :: 3.8
Classifier: Programming Language :: Python :: Implementation :: CPython
Classifier: Programming Language :: Python :: Implementation :: PyPy
Classifier: Topic :: Software Development :: Testing
Requires-Dist: pytest (>=8.0.0,<9.0.0)
Requires-Dist: pytest-metadata (>=3.1.1,<4.0.0)
